{
	"Delete Subreco": "Delete subrecord",
	"OK": "Accept",
	"Add": "Add a new record",
	"Close": "Close",
	"Chart": "Display Chart editor...",
	"Previous Page": "Previous Page",
	"Next Page": "Next Page",
	"Add Subrecord": "Add a new subrecord",
	"Open": "Open subrecord",
	"Use@": "Enter the client number or @ to see the complete list",
	"First Record": "First Record",
	"Previous Record": "Previous Record",
	"Next Record": "Next Record",
	"Last Record": "Last Record",
	"Delete Record": "Delete Record",
	"Cancel": "Cancel",
	"Record Number": "Record Position within Selection",
	"Delete Selectio": "Delete Highlighted Records",
	"Show All": "Select All Records",
	"Query": "Query",
	"Order By": "Order by",
	"Report": "Quick Reports",
	"Print Labels": "Print Labels",
	"Graph Table": "Graphs and Charts",
	"Done": "Done",
	"Add Record": "Add a New Record",
	"Show Subset": "Select Highlighted Records",
	"Print Selection": "Print",
	"First Page": "First Page",
	"Last Page": "Last Page"
}